i18n_utils/__init__.py
i18n_utils/normalization.py
i18n_utils/params.py
i18n_utils/styles.py
i18n_utils/utils.py
i18n_utils/cli/__init__.py
i18n_utils/cli/msgdiff.py
i18n_utils/cli/msgfromxls.py
i18n_utils/cli/msgnorm.py
i18n_utils/cli/msgtoxls.py
i18n_utils-0.0.3.dist-info/DESCRIPTION.rst
i18n_utils-0.0.3.dist-info/entry_points.txt
i18n_utils-0.0.3.dist-info/METADATA
i18n_utils-0.0.3.dist-info/metadata.json
i18n_utils-0.0.3.dist-info/RECORD
i18n_utils-0.0.3.dist-info/top_level.txt
i18n_utils-0.0.3.dist-info/WHEEL
