Metadata-Version: 2.0
Name: i18n-utils
Version: 0.0.3
Summary: A collection of utilities to add functionality to the gettext commands.
Home-page: https://github.com/GaretJax/i18n-utils
Author: Jonathan Stoppani
Author-email: jonathan@stoppani.name
License: MIT
Platform: UNKNOWN
Classifier: Development Status :: 4 - Beta
Classifier: Intended Audience :: Developers
Classifier: License :: OSI Approved :: MIT License
Classifier: Operating System :: OS Independent
Classifier: Programming Language :: Python
Classifier: Programming Language :: Python :: 3
Classifier: Programming Language :: Python :: 3.3
Classifier: Programming Language :: Python :: 3.4
Requires-Dist: click (==3.3)
Requires-Dist: jdcal (==1.0.1)
Requires-Dist: openpyxl (==2.2.0b1)
Requires-Dist: polib (==1.0.6)
Requires-Dist: six (==1.9.0)
